lsre/__init__.py
lsre/regex_functions.py
lsre/utils.py
lsre-0.1.4.dist-info/WHEEL
lsre-0.1.4.dist-info/METADATA
lsre-0.1.4.dist-info/RECORD
