Metadata-Version: 2.3
Name: lsre
Version: 0.1.4
Summary: A project to learn simple regular expressions.
Author: Rohit Gupta
Author-email: Rohit Gupta <gupta.rohit21198@gmail.com>
Classifier: License :: OSI Approved :: MIT License
Classifier: Programming Language :: Python :: 3.12
Classifier: Programming Language :: Python :: 3.13
Requires-Dist: hydra-core>=1.3.2
Requires-Dist: loguru>=0.7.3
Requires-Dist: python-dotenv>=1.0.1
Requires-Python: >=3.12.8
